dichback/Dichback.py
dichback/__init__.py
dichback-0.0.9.dist-info/LICENSE
dichback-0.0.9.dist-info/METADATA
dichback-0.0.9.dist-info/WHEEL
dichback-0.0.9.dist-info/top_level.txt
dichback-0.0.9.dist-info/RECORD
