Metadata-Version: 2.1
Name: dichback
Version: 0.0.9
Summary: 二分回溯算法，通过逻辑和-逻辑函数单元在有效数据集中查找符合逻辑单元判别条件的数据子集
Home-page: https://github.com/SpeechlessMatt/Dichback
Author: Czy_4201b
Author-email: speechlessmatt@qq.com
License: MIT
Classifier: Programming Language :: Python :: 3
Classifier: License :: OSI Approved :: MIT License
Classifier: Operating System :: OS Independent
License-File: LICENSE
